{
  "あるの": [
    "アルノ",
    "有乃"
  ],
  "あるん": [
    "アルン"
  ],
  "いためる": [
    "イタめる"
  ],
  "いちいち": [
    "一一",
    "市市"
  ],
  "かくの": [
    "角野",
    "カクノ",
    "格野",
    "覚埜",
    "覚野",
    "覺野",
    "角埜",
    "郭野",
    "加來野",
    "加来野"
  ],
  "かっ": [
    "核"
  ],
  "かな": [
    "哉"
  ],
  "ぎのざ": [
    "宣野座"
  ],
  "する": [
    "スる"
  ],
  "ぜ": [
    "世",
    "是"
  ],
  "そう": [
    "ソウ"
  ],
  "そうな": [
    "哨吶",
    "奏奈",
    "惣名",
    "想奈",
    "聡奈",
    "聡菜",
    "蒼南",
    "蒼那",
    "霜奈",
    "颯奈",
    "颯菜"
  ],
  "たいて": [
    "泰輝"
  ],
  "だが": [
    "駄賀"
  ],
  "だな": [
    "棚"
  ],
  "だね": [
    "種"
  ],
  "できる": [
    "デキル",
    "デキる"
  ],
  "なう": [
    "綯う"
  ],
  "なの": [
    "七",
    "奴",
    "名野",
    "奈乃",
    "奈希",
    "梛乃",
    "楠乃",
    "菜乃",
    "菜野"
  ],
  "なるほど": [
    "なァる程",
    "なアるほど",
    "ナルホド"
  ],
  "のか": [
    "ノカ"
  ],
  "ほんもの": [
    "本もの",
    "ほんもの",
    "ホンモノ"
  ],
  "もも": [
    "喪々",
    "望茂",
    "望萌",
    "桃百",
    "茂々",
    "茂萌",
    "萌百",
    "萌茂"
  ],
  "やっぱり": [
    "やッぱり",
    "矢ッ張り",
    "矢ツぱり"
  ]
}
